dcspy/__init__.py
dcspy/aircraft.py
dcspy/dcsbios.py
dcspy/log.py
dcspy/logitech.py
dcspy/migration.py
dcspy/models.py
dcspy/py.typed
dcspy/qt_gui.py
dcspy/qtgui_rc.py
dcspy/run.py
dcspy/starter.py
dcspy/utils.py
dcspy/img/dcspy_black.ico
dcspy/img/dcspy_white.ico
dcspy/img/splash.png
dcspy/resources/AH-64D_BLK_II.yaml
dcspy/resources/AV8BNA.yaml
dcspy/resources/F-14A-135-GR.yaml
dcspy/resources/F-14B.yaml
dcspy/resources/F-15ESE.yaml
dcspy/resources/F-16C_50.yaml
dcspy/resources/F-4E-45MC.yaml
dcspy/resources/FA-18C_hornet.yaml
dcspy/resources/Ka-50.yaml
dcspy/resources/Ka-50_3.yaml
dcspy/resources/LogitechGkeyLib.h
dcspy/resources/LogitechLCDLib.h
dcspy/resources/LogitechLEDLib.h
dcspy/resources/config.yaml
dcspy/resources/falconded.ttf
dcspy/resources/license.txt
dcspy/sdk/__init__.py
dcspy/sdk/key_sdk.py
dcspy/sdk/lcd_sdk.py
dcspy/sdk/led_sdk.py
dcspy-3.7.1.dist-info/licenses/LICENSE.md
dcspy-3.7.1.dist-info/licenses/src/dcspy/resources/license.txt
dcspy-3.7.1.dist-info/METADATA
dcspy-3.7.1.dist-info/WHEEL
dcspy-3.7.1.dist-info/entry_points.txt
dcspy-3.7.1.dist-info/top_level.txt
dcspy-3.7.1.dist-info/RECORD
