Metadata-Version: 2.4
Name: dcspy
Version: 3.7.1
Summary: Software for integrating DCS Planes with Logitech keyboards (with and without LCD), mice and headphones.
Author: Michal Plichta
Maintainer: Michal Plichta
License-Expression: MIT
Project-URL: Homepage, https://github.com/emcek/dcspy
Project-URL: Documentation, https://dcspy.readthedocs.io/en/latest/
Project-URL: Source, https://github.com/emcek/dcspy.git
Project-URL: Changelog, https://github.com/emcek/dcspy/blob/master/CHANGELOG.md
Keywords: dcsworld,dcs,digital combat simulator,eagle dynamics,logitech,logitech sdk,logitech keyboard,logitech gaming,logitech mouse,logitech headphone,G19,G510,G15,G13,G910,G710,G110,G103,G105,G11,G35,G633,G930,G933,G600,G300,G400,G700,G9,MX518,G402,G502,G602
Classifier: Development Status :: 5 - Production/Stable
Classifier: Environment :: Console
Classifier: Environment :: Win32 (MS Windows)
Classifier: Programming Language :: Python :: 3.9
Classifier: Programming Language :: Python :: 3.10
Classifier: Programming Language :: Python :: 3.11
Classifier: Programming Language :: Python :: 3.12
Classifier: Programming Language :: Python :: 3.13
Classifier: Operating System :: Microsoft :: Windows
Classifier: Operating System :: Microsoft :: Windows :: Windows 10
Classifier: Operating System :: Microsoft :: Windows :: Windows 11
Classifier: Topic :: Games/Entertainment
Classifier: Topic :: Games/Entertainment :: Simulation
Classifier: Topic :: Software Development :: Libraries :: Python Modules
Classifier: Topic :: System :: Hardware
Classifier: Topic :: Utilities
Requires-Python: >=3.9
License-File: LICENSE.md
License-File: src/dcspy/resources/license.txt
Requires-Dist: cffi
Requires-Dist: eval-type-backport; python_version < "3.10"
Requires-Dist: gitpython
Requires-Dist: lupa
Requires-Dist: packaging
Requires-Dist: pillow
Requires-Dist: psutil
Requires-Dist: pydantic
Requires-Dist: pyside6
Requires-Dist: pyyaml
Requires-Dist: requests
Requires-Dist: typing-extensions
Provides-Extra: test
Requires-Dist: interrogate; extra == "test"
Requires-Dist: isort; extra == "test"
Requires-Dist: lxml; extra == "test"
Requires-Dist: mypy; extra == "test"
Requires-Dist: pip-audit; extra == "test"
Requires-Dist: pytest; extra == "test"
Requires-Dist: pytest-codspeed; extra == "test"
Requires-Dist: pytest-cov; extra == "test"
Requires-Dist: pytest-qt; sys_platform == "win32" and extra == "test"
Requires-Dist: pytest-randomly; extra == "test"
Requires-Dist: ruff; extra == "test"
Requires-Dist: types-cffi; extra == "test"
Requires-Dist: types-lupa; extra == "test"
Requires-Dist: types-pillow; extra == "test"
Requires-Dist: types-psutil; extra == "test"
Requires-Dist: types-pyyaml; extra == "test"
Requires-Dist: types-requests; extra == "test"
Provides-Extra: docs
Requires-Dist: black; extra == "docs"
Requires-Dist: mkdocs; extra == "docs"
Requires-Dist: mkdocs-gen-files; extra == "docs"
Requires-Dist: mkdocs-literate-nav; extra == "docs"
Requires-Dist: mkdocs-material; extra == "docs"
Requires-Dist: mkdocs-plantuml; extra == "docs"
Requires-Dist: mkdocs-section-index; extra == "docs"
Requires-Dist: mkdocstrings; extra == "docs"
Requires-Dist: mkdocstrings-python; extra == "docs"
Requires-Dist: plantuml; extra == "docs"
Dynamic: license-file
